tickytacky/__init__.py
tickytacky/clock.py
tickytacky/run_app.py
tickytacky/scene.py
tickytacky/screen.py
tickytacky/sprite.py
tickytacky-0.10.0.dist-info/LICENSE
tickytacky-0.10.0.dist-info/WHEEL
tickytacky-0.10.0.dist-info/METADATA
tickytacky-0.10.0.dist-info/RECORD
