Metadata-Version: 2.1
Name: tickytacky
Version: 0.10.0
Summary: Tickytacky pixel game maker
License: GNU General Public License
Author: JP Etcheber
Author-email: jetcheber@gmail.com
Requires-Python: >=3.8,<3.11
Classifier: License :: Other/Proprietary License
Classifier: Programming Language :: Python :: 3
Classifier: Programming Language :: Python :: 3.10
Classifier: Programming Language :: Python :: 3.8
Classifier: Programming Language :: Python :: 3.9
Requires-Dist: Flask (>=2.1.2,<3.0.0)
Requires-Dist: Pillow (>=9.1.0,<10.0.0)
Requires-Dist: pyglet (>=1.5.23,<2.0.0)
